README.md
setup.py
distributions_by_rrod/Binomialdistribution.py
distributions_by_rrod/Gaussiandistribution.py
distributions_by_rrod/Generaldistribution.py
distributions_by_rrod/__init__.py
distributions_by_rrod.egg-info/PKG-INFO
distributions_by_rrod.egg-info/SOURCES.txt
distributions_by_rrod.egg-info/dependency_links.txt
distributions_by_rrod.egg-info/not-zip-safe
distributions_by_rrod.egg-info/top_level.txt