Metadata-Version: 2.1
Name: distributions-by-rrod
Version: 0.1
Summary: Gaussian and Binomial distributions
Home-page: UNKNOWN
Author: R. Rodriguez
License: UNKNOWN
Platform: UNKNOWN
